Workbook

Sheet Front page
F10: TAMIL NADU VETERINARY AND ANIMAL SCIENCEAS UNIVERSITY
F11: VETERINARY COLLEGE AND RESEARCH INSTITUTE, NAMAKKAL
F12: DEPARTMENT OF ANIMAL HUSBANDRY ECONOMICS
H13: PROJECT REPORT ON GOAT FARMING
F15: Title of the Project: | G15: Development of specialized computer software to assist veterinary professionals in creating bankable livestock and poultry farming project report
H16: Under Tamil Nadu GovernmentScheme on
I17: "Students - Entrepreneurs - Industrialists Conclave: Showcasing, refinement and support for commersialization of the innovations of students in the field of Veterinary and Animal Sciences"
G19: Name of the Student
G20: DHARSHID VINESH, U.R. BVN 23018
G21: DHARSHIKA, K BVN 23038
G22: III PFY, B.V.Sc., & A.H., 2023-24 Batch
G24: Name of the Mentor
H25: Dr. V. Senthilkumar, M.V.Sc., Ph.D.,
H26: Professor and Head,
H27: Department of Animal Husbandry Economics
H28: Veterinary College and Reasearch Institute
H29: Namakkal 637 002

Sheet Project at a glance
C3: PROJECT REPORT ON DAIRY FARMING
C5: PROJECT AT A GLANCE
A6: 1 | B6: Name of the Farmer/Unit
A7: 2 | B7: Address of the Farmer
A8: 3 | B8: Aadhar Number (Optional)
A9: 4 | B9: Mobile Number
A10: 5 | B10: E mail Id (Optional)
A11: 6 | B11: Nature of the Farming / Activity
B12: Number of animals
A13: 7 | B13: Address location of the Farm
A14: 8 | B14: Name of the Financing Bank
A15: 9 | B15: Name of the Branch
A16: 10 | B16: PROJECT COST
B17: Capital and Machineary Investment (in Rs.) | C17: =Investment!C27 -> 1688100
B18: Working Capital (in Rs.) | C18: =Investment!C45 -> 793600
B19: Total Cost of the Project (in Rs.) | C19: =Investment!C46 -> 2481700
A20: 11 | B20: MEANS OF FINANCE
B21: Bank Loan (in Rs.) | C21: =Investment!C49 -> 2357615
B22: Margin Money (in Rs.) | C22: =Investment!C50 -> 124085
B23: Total (in Rs.) | C23: =Investment!C52 -> 868595
B24: Subsidy (in Rs.)
B25: Name of Subsidy Programme
B26: Rate of Interest (in percent / annum) | C26: ='Techno Economic Parameters'!C47 -> 11.5
B27: Repayment Period (in years) | C27: ='Techno Economic Parameters'!C48 -> 7
A28: 12 | B28: Project evaluation Values
B29: NPV | C29: ='Financial Analysis'!F15 -> 7702670.4
B30: BCR | C30: ='Financial Analysis'!F16 -> 2.6047446
B31: IRR (in per cent) | C31: ='Financial Analysis'!E28 -> 24.190456
B32: DSCR | C32: ='Financial Analysis'!E38 -> 4.0667979
A33: 13 | B33: Employment opportunities(in No. of labour)

Sheet Techno Economic Parameters
C3: PROJECT REPORT ON GOAT FARMING
B5: TECHNO ECONOMIC PARAMETERS
B6: ANIMAL
B7: Type of Animal | C7: Goat
B8: System of Rearing | C8: Stall Fed Rearing | D8: Semi Intensive
B9: Name of the Breed | C9: Tellicherry | D9: Boer | E9: Indigenous
C10: Male - Buck | D10: Female - Doe
B11: Unit Size (No. of Animals) | C11: 5 | D11: 100
B12: Purchase cost of Male Animals (Rs./Animal) | C12: 12000
B13: Purchase cost of Female Animals (Rs./Animal) | C13: 10000
B14: Insurance Premium (in percent / animal / annum) | C14: 6
B15: Transport Charges (Rs./Animal) | C15: 100
B17: SHED/BUILDING | E17: Standard
B18: Floor Space Requirement for Male Animal (Sq.ft/Buck) | C18: 20 | E18: 15-20 sq.ft | F18: per adult
B19: Floor Space Requirement for Female Animal (Sq.ft/Doe) | C19: 10
B20: Floor Space Requirement for Kids (Sq.ft/Kid) | C20: 4 | E20: 3-5 sq.ft | F20: per kid
B21: Cost of Construction for Shed for Buck, Doe and Kid (Rs./Sq.ft) | C21: 350
B22: Floor Space Requirement for Store Room (in Sq.ft) | C22: 0
B23: Cost of Construction for Store Room (Rs./Sq.ft) | C23: 0
B25: EQUIPMENT
B26: Cost of Equipment for Adult Animal (Rs./animal) | C26: 20
B27: Cost of Equipment for Kids (Rs./Kid) | C27: 10
B28: Requirement for number of Chaff Cutter (in nos.) | C28: 1
B29: Cost of Chaff Cutter (in Rs./Chaff cutter) | C29: 30000
B30: Cost of Brush Cutter (in Rs.) | C30: 0
B31: Cost of Mini Feed Making Machinery (in Rs.) | C31: 0
B32: Cost of Motor for irrigation facilities (in Rs.) | C32: 0
B33: Cost of Sprinkler and Fogger | C33: 20000
B34: Cost of Computers (in Rs.) | C34: 0
B35: Cost of CCTV (in Rs.) | C35: 0
B37: OTHER INFRASTRUCTURE
B38: Floor Space Requirement for Labour Quarters (in Sq.ft) | C38: 0
B39: Cost of Construction for Labour Quarters (Rs./Sq.ft) | C39: 0
B40: Cost of Establishment of Overhead Tank/Water storage Tank (in Rs.) | C40: 0
B41: Cost of Fencing for Goat Shed (in Rs.) | C41: 50000
B42: Land leveling Charges (in Rs.) | C42: 0
B43: Digging of Borewell (in Rs.) | C43: 0
C44: 0
B45: MENAS OF FINANCE
B46: Margin Money (in percent) | C46: 5
B47: Rate of Interets (in percent) | C47: 11.5
B48: Repayment Period (in years) | C48: 7
B49: Subsidy (in percent to the total cost of the project) | C49: 35
B51: VEHICLE
B52: Number of Two Wheeler (in Nos.) | C52: 0
B53: Cost of Vehicle (in Rs./Vehicle) | C53: 0
B54: Number of Four Wheeler (in Nos.) | C54: 0
B55: Cost of Vehicle (in Rs./Vehicle) | C55: 0
B57: EXPENSES
B58: Concentrate Feed Requirement for Buck (Kg/day/Buck) | C58: 0.3
B59: Concentrate Feed Requirement for Doe (Kg/day/Doe) | C59: 0.2
B60: Concentrate Feed Requiremnt for Kid (Kg/day/Kid) | C60: 0.1
B61: Cost of Concentrate Feed (Rs./kg) | C61: 23
B62: Cost of Dry Fodder (Rs./annum) | C62: 50000
B63: Green Fodder Area Requirement (in acres) | C63: 2
B64: Green Fodder Field Establishment in First Year (Rs./acre) | C64: 5000
B65: Green Fodder Production from Second Year onwards (Rs./acre) | C65: 3000
B66: Veterinary Aid for Adult Animal (Rs./animal/annum) | C66: 50
B67: Veterinary Aid for Kid (Rs./Kid/annum) | C67: 20
B68: Electricity Charges (Rs./month) | C68: 400
B69: Fuel Charges (Rs./month) | C69: 0
... B73: Expenses for Feed Making Unit (Rs./annum) | C73: 0
B75: PRODUCTION
B76: Kidding interval (in months) | C76: 8
B77: Conception Rate (in Per cent /annum) | C77: 90
B78: Kidding Percentage (in per cent/annum) | C78: 80
B79: Culling Percentage (in per cent / annum) | C79: 10
B80: Average Litter Size (single, twinning and triplet - in nos./birth) | C80: 2
B81: Number of kidding (in nos per doe per annum) | C81: 2
B82: Saleable age of kids (in months) | C82: 11
B83: Mortality of kids (in per cent / annum) | C83: 10
B84: LABOUR
B85: No. of Labour Required for Farm Work (in nos) | C85: 1
B86: Wages for Farm Worker (in Rs./month) | C86: 10000
B87: No. of Farm Manager Required (in nos) | C87: 0
B88: salary for Farm manager (in Rs./month) | C88: 0
B89: No. of Drivers Required (in nos) | C89: 0
B90: Salary for Driver (in Rs./month) | C90: 0
B91: No. of Office Staff Required (in nos) | C91: 0
B92: Salary for Office Staff (in Rs./month) | C92: 0
B94: RETURNS
B95: Sale Price of Male KIds (Rs./Kid ) | C95: 8000
B96: Sale Price of Female Kids (Rs./Kid) | C96: 7000
B97: sale Price of Culled animal (Rs./animal) | C97: 7000
B98: Income from Mannure (Rs./animal/annum) | C98: 50

Sheet Investment
B2: INVESTMENT OF THE PROJECT
B5: CAPITAL/FIXED INVESTMENT | E5: Fixed Investment : It refers to buying /constructing long term physical assets such as animals, sheds and equipments.
B6: Cost of Buck | C6: ='Techno Economic Parameters'!C11*'Techno Economic Parameters'!C12 -> 60000
B7: Cost of Doe | C7: =ROUNDDOWN(('Techno Economic Parameters'!D11*'Techno Economic Parameters'!C13),-2) -> 1000000
B8: Coat of Construction for Adult Animal Shed | C8: =('Techno Economic Parameters'!C11*'Techno Economic Parameters'!C18*'Techno Economic Parameters'!C21)+('Techno Economic Parameters'!D11*'Techno Economic Parameters'!C19*'Techno Economic Parameters'!C21) -> 385000
B9: Cost of Construction for Kid Pen | C9: ='Techno Economic Parameters'!D11*'Techno Economic Parameters'!C20*'Techno Economic Parameters'!C21 -> 140000
B10: Cost of Construction for Store Room | C10: ='Techno Economic Parameters'!C22*'Techno Economic Parameters'!C23 -> 0
B11: Cost of Construction for Labour Quarters | C11: ='Techno Economic Parameters'!C38*'Techno Economic Parameters'!C39 -> 0
B12: Cost of Equipment for Adult Animal | C12: =('Techno Economic Parameters'!C11+'Techno Economic Parameters'!D11)*'Techno Economic Parameters'!C26 -> 2100
B13: Cost of Equipment for kids | C13: ='Techno Economic Parameters'!D11*'Techno Economic Parameters'!C27 -> 1000
B14: Cost of Chaff Cutter | C14: ='Techno Economic Parameters'!C28*'Techno Economic Parameters'!C29 -> 30000
B15: Cost of Brush Cutter | C15: ='Techno Economic Parameters'!C30 -> 0
B16: Cost of Mini Feed Making Machinery | C16: ='Techno Economic Parameters'!C31 -> 0
B17: Cost of Motor for Irrigation Facilities | C17: ='Techno Economic Parameters'!C32 -> 0
B18: Cost of Sprinkler and Fogger | C18: ='Techno Economic Parameters'!C33 -> 20000
B19: Cost of Establishment of Overhead Tank | C19: ='Techno Economic Parameters'!C40 -> 0
B20: Cost of Fencing for Goat Shed | C20: ='Techno Economic Parameters'!C41 -> 50000
B21: Land leveling Charges | C21: ='Techno Economic Parameters'!C42 -> 0
B22: Digging of Borewell | C22: ='Techno Economic Parameters'!C43 -> 0
B23: Cost of Vehicle | C23: =(('Techno Economic Parameters'!C52*'Techno Economic Parameters'!C53)+('Techno Economic Parameters'!C54+'Techno Economic Parameters'!C55)) -> 0
B24: Cost of Computers | C24: ='Techno Economic Parameters'!C34 -> 0
B25: Cost of CCTV | C25: ='Techno Economic Parameters'!C35 -> 0
B27: Total Capital Investment | C27: =ROUNDDOWN(SUM(C6:C26),-2) -> 1688100
B29: WORKING CAPITAL - ONE YEAR | E29: Working Capital: It represents the funds required to operate day to day farming expenses up to the certain period of receiving income.
B30: Insurance Premium | C30: =(C6+C7)*'Techno Economic Parameters'!C14% -> 63600
B31: Transport Charges | C31: =('Techno Economic Parameters'!C11+'Techno Economic Parameters'!D11)*'Techno Economic Parameters'!C15 -> 10500
B32: Cost of Concentrate Feed | C32: =((('Techno Economic Parameters'!C11*'Techno Economic Parameters'!C58)+('Techno Economic Parameters'!D11*'Techno Economic Parameters'!C59)+('Techno Economic Parameters'!D11*4*'Techno Economic Parameters'!C60))*'Techno Economic Parameters'!C61)*365 -> 516292.5
B33: Cost of Dry Fodder | C33: ='Techno Economic Parameters'!C62 -> 50000
B34: Cost of Green Fodder | C34: ='Techno Economic Parameters'!C63*'Techno Economic Parameters'!C64 -> 10000
B35: Labour Wages | C35: =((('Techno Economic Parameters'!C85*'Techno Economic Parameters'!C86)+('Techno Economic Parameters'!C87*'Techno Economic Parameters'!C88)+('Techno Economic Parameters'!C89*'Techno Economic Parameters'!C90)+('Techno Economic Parameters'!C91*'Techno Economic Parameters'!C92))*12) -> 120000
B36: Veterinary Expenses | C36: =((('Techno Economic Parameters'!C11+'Techno Economic Parameters'!D11)*'Techno Economic Parameters'!C66)+('Techno Economic Parameters'!D11*4*'Techno Economic Parameters'!C67)) -> 13250
B37: Electricity Expenses | C37: ='Techno Economic Parameters'!C68*12 -> 4800
B38: Fuel Expenses | C38: ='Techno Economic Parameters'!C69*12 -> 0
B39: Miscellaneous Expenses | C39: ='Techno Economic Parameters'!C72*('Techno Economic Parameters'!C11+'Techno Economic Parameters'!D11) -> 5250
B40: Expenses for Feed Making Unit | C40: ='Techno Economic Parameters'!C73 -> 0
B45: Total Working Capital | C45: =ROUNDDOWN(SUM(C30:C44),-2) -> 793600
B46: Total Cost of the Project | C46: =ROUNDDOWN((C27+C45),-2) -> 2481700
B48: MEANS OF FINANCE
B49: Loan From Bank | C49: =C46-C50 -> 2357615
B50: Margin Money | C50: =C46*'Techno Economic Parameters'!C46% -> 124085
B51: Total | C51: =C49+C50 -> 2481700 | E51: Margin Money: Farmer/Beneficiary Contribution to the total project cost. Range about 5 to 25 per cent
B52: Subsidy | C52: =C46*'Techno Economic Parameters'!C49% -> 868595 | E52: Subsidy : Various rate of susbsidy avaiable depends on the scheme announced by Government

Sheet Production Chart
D2: FLOCK PROJECTION CHART
B6: Particulars | D6: I Year | E6: II Year | F6: III Year | G6: IV Year | H6: V Year | I6: VI Year | J6: VII Year
B7: Number of does purchased | C7: ='Techno Economic Parameters'!D11 -> 100
B8: Number of bucks purchased | C8: ='Techno Economic Parameters'!C11 -> 5
B9: Number of kidding per year | C9: ='Techno Economic Parameters'!C81 -> 2 | D9: =C9 -> 2 | E9: =D9 -> 2 | F9: =E9 -> 2 | G9: =F9 -> 2 | H9: =G9 -> 2 | I9: =H9 -> 2 | J9: =I9 -> 2
B10: Number of kid per kidding/litter | C10: ='Techno Economic Parameters'!C80 -> 2 | D10: =C10 -> 2 | E10: =D10 -> 2 | F10: =E10 -> 2 | G10: =F10 -> 2 | H10: =G10 -> 2 | I10: =H10 -> 2 | J10: =I10 -> 2
B11: Number of male kids born | C11: =(C7*C10*C9)/2 -> 200 | D11: =C11 -> 200 | E11: =D11 -> 200 | F11: =E11 -> 200 | G11: =F11 -> 200 | H11: =G11 -> 200 | I11: =H11 -> 200 | J11: =I11 -> 200
B12: Number of male kids mortality | C12: =C11*'Techno Economic Parameters'!C83% -> 20 | D12: =C12 -> 20 | E12: =D12 -> 20 | F12: =E12 -> 20 | G12: =F12 -> 20 | H12: =G12 -> 20 | I12: =H12 -> 20 | J12: =I12 -> 20
B13: Number of female kids born | C13: =(C7*C10*C9)/2 -> 200 | D13: =C13 -> 200 | E13: =D13 -> 200 | F13: =E13 -> 200 | G13: =F13 -> 200 | H13: =G13 -> 200 | I13: =H13 -> 200 | J13: =I13 -> 200
B14: Number of female kids mortality | C14: =C13*'Techno Economic Parameters'!C83% -> 20 | D14: =C14 -> 20 | E14: =D14 -> 20 | F14: =E14 -> 20 | G14: =F14 -> 20 | H14: =G14 -> 20 | I14: =H14 -> 20 | J14: =I14 -> 20
B15: Number of male kids as replacement stock | C15: =(C11*2%)/2 -> 2 | D15: =C15 -> 2 | E15: =D15 -> 2 | F15: =E15 -> 2 | G15: =F15 -> 2 | H15: =G15 -> 2 | I15: =H15 -> 2 | J15: =I15 -> 2
B16: Number of female kids as replacement sotck | C16: =C13*2% -> 4 | D16: =C16 -> 4 | E16: =D16 -> 4 | F16: =E16 -> 4 | G16: =F16 -> 4 | H16: =G16 -> 4 | I16: =H16 -> 4 | J16: =I16 -> 4
B17: Number of male kids available for sale | C17: =C11-(C12+C15) -> 178 | D17: =C17 -> 178 | E17: =D17 -> 178 | F17: =E17 -> 178 | G17: =F17 -> 178 | H17: =G17 -> 178 | I17: =H17 -> 178 | J17: =I17 -> 178
B18: Number of female kids available for sale | C18: =C13-(C14+C16) -> 176 | D18: =C18 -> 176 | E18: =D18 -> 176 | F18: =E18 -> 176 | G18: =F18 -> 176 | H18: =G18 -> 176 | I18: =H18 -> 176 | J18: =I18 -> 176
B19: Number of adult male culled | C19: =C15/2 -> 1 | D19: =C19 -> 1 | E19: =D19 -> 1 | F19: =E19 -> 1 | G19: =F19 -> 1 | H19: =G19 -> 1 | I19: =H19 -> 1 | J19: =I19 -> 1
B20: Number of female adult culled | C20: =C16 -> 4 | D20: =C20 -> 4 | E20: =D20 -> 4 | F20: =E20 -> 4 | G20: =F20 -> 4 | H20: =G20 -> 4 | I20: =H20 -> 4 | J20: =I20 -> 4

Sheet Expenditure Income 
C2: EXPENDITURE INCOME STATEMENT
C4: I Year | D4: II Year | E4: III Year | F4: IV Year | G4: V Year | H4: VI Year | I4: VII Year
B5: Expenditure
B6: Insurance Premium | C6: =Investment!$C$30 -> 63600 | D6: =Investment!$C$30 -> 63600 | E6: =Investment!$C$30 -> 63600 | F6: =Investment!$C$30 -> 63600 | G6: =Investment!$C$30 -> 63600 | H6: =Investment!$C$30 -> 63600 | I6: =Investment!$C$30 -> 63600
B7: Transport Charges | C7: =Investment!C31 -> 10500 | D7: 0 | E7: 0 | F7: 0 | G7: 0 | H7: 0 | I7: 0
B8: Cost of Concentrate Feed | C8: =Investment!$C$32 -> 516292.5 | D8: =Investment!$C$32 -> 516292.5 | E8: =Investment!$C$32 -> 516292.5 | F8: =Investment!$C$32 -> 516292.5 | G8: =Investment!$C$32 -> 516292.5 | H8: =Investment!$C$32 -> 516292.5 | I8: =Investment!$C$32 -> 516292.5
B9: Cost of Dry Fodder | C9: =Investment!$C$33 -> 50000 | D9: =Investment!$C$33 -> 50000 | E9: =Investment!$C$33 -> 50000 | F9: =Investment!$C$33 -> 50000 | G9: =Investment!$C$33 -> 50000 | H9: =Investment!$C$33 -> 50000 | I9: =Investment!$C$33 -> 50000
B10: Cost of Green Fodder | C10: =Investment!$C$34 -> 10000 | D10: =Investment!$C$34 -> 10000 | E10: =Investment!$C$34 -> 10000 | F10: =Investment!$C$34 -> 10000 | G10: =Investment!$C$34 -> 10000 | H10: =Investment!$C$34 -> 10000 | I10: =Investment!$C$34 -> 10000
B11: Labour Wages | C11: =((('Techno Economic Parameters'!$C$85*'Techno Economic Parameters'!$C$86)+('Techno Economic Parameters'!$C$87*'Techno Economic Parameters'!$C$88)+('Techno Economic Parameters'!$C$89*'Techno Economic Parameters'!$C$90)+('Techno Economic Parameters'!$C$91*'Techno Economic Parameters'!$C$92))*12) -> 120000 | D11: =((('Techno Economic Parameters'!$C$85*'Techno Economic Parameters'!$C$86)+('Techno Economic Parameters'!$C$87*'Techno Economic Parameters'!$C$88)+('Techno Economic Parameters'!$C$89*'Techno Economic Parameters'!$C$90)+('Techno Economic Parameters'!$C$91*'Techno Economic Parameters'!$C$92))*12) -> 120000 | E11: =((('Techno Economic Parameters'!$C$85*'Techno Economic Parameters'!$C$86)+('Techno Economic Parameters'!$C$87*'Techno Economic Parameters'!$C$88)+('Techno Economic Parameters'!$C$89*'Techno Economic Parameters'!$C$90)+('Techno Economic Parameters'!$C$91*'Techno Economic Parameters'!$C$92))*12) -> 120000 | F11: =((('Techno Economic Parameters'!$C$85*'Techno Economic Parameters'!$C$86)+('Techno Economic Parameters'!$C$87*'Techno Economic Parameters'!$C$88)+('Techno Economic Parameters'!$C$89*'Techno Economic Parameters'!$C$90)+('Techno Economic Parameters'!$C$91*'Techno Economic Parameters'!$C$92))*12) -> 120000 | G11: =((('Techno Economic Parameters'!$C$85*'Techno Economic Parameters'!$C$86)+('Techno Economic Parameters'!$C$87*'Techno Economic Parameters'!$C$88)+('Techno Economic Parameters'!$C$89*'Techno Economic Parameters'!$C$90)+('Techno Economic Parameters'!$C$91*'Techno Economic Parameters'!$C$92))*12) -> 120000 | H11: =((('Techno Economic Parameters'!$C$85*'Techno Economic Parameters'!$C$86)+('Techno Economic Parameters'!$C$87*'Techno Economic Parameters'!$C$88)+('Techno Economic Parameters'!$C$89*'Techno Economic Parameters'!$C$90)+('Techno Economic Parameters'!$C$91*'Techno Economic Parameters'!$C$92))*12) -> 120000 | I11: =((('Techno Economic Parameters'!$C$85*'Techno Economic Parameters'!$C$86)+('Techno Economic Parameters'!$C$87*'Techno Economic Parameters'!$C$88)+('Techno Economic Parameters'!$C$89*'Techno Economic Parameters'!$C$90)+('Techno Economic Parameters'!$C$91*'Techno Economic Parameters'!$C$92))*12) -> 120000
B12: Veterinary Expenses | C12: =Investment!$C$36 -> 13250 | D12: =Investment!$C$36 -> 13250 | E12: =Investment!$C$36 -> 13250 | F12: =Investment!$C$36 -> 13250 | G12: =Investment!$C$36 -> 13250 | H12: =Investment!$C$36 -> 13250 | I12: =Investment!$C$36 -> 13250
B13: Electricity Expenses | C13: =Investment!$C$37 -> 4800 | D13: =Investment!$C$37 -> 4800 | E13: =Investment!$C$37 -> 4800 | F13: =Investment!$C$37 -> 4800 | G13: =Investment!$C$37 -> 4800 | H13: =Investment!$C$37 -> 4800 | I13: =Investment!$C$37 -> 4800
B14: Fuel Expenses | C14: =Investment!$C$38 -> 0 | D14: =Investment!$C$38 -> 0 | E14: =Investment!$C$38 -> 0 | F14: =Investment!$C$38 -> 0 | G14: =Investment!$C$38 -> 0 | H14: =Investment!$C$38 -> 0 | I14: =Investment!$C$38 -> 0
B15: Miscellaneous Expenses | C15: =Investment!$C$39 -> 5250 | D15: =Investment!$C$39 -> 5250 | E15: =Investment!$C$39 -> 5250 | F15: =Investment!$C$39 -> 5250 | G15: =Investment!$C$39 -> 5250 | H15: =Investment!$C$39 -> 5250 | I15: =Investment!$C$39 -> 5250
B16: Expenses for Feed Making Unit | C16: =Investment!$C$40 -> 0 | D16: =Investment!$C$40 -> 0 | E16: =Investment!$C$40 -> 0 | F16: =Investment!$C$40 -> 0 | G16: =Investment!$C$40 -> 0 | H16: =Investment!$C$40 -> 0 | I16: =Investment!$C$40 -> 0
B17: Interest | C17: =SUM(Repayment!E11:E22) -> 271125.72 | D17: =SUM(Repayment!E23:E34) -> 259109.65 | E17: =SUM(Repayment!E35:E46) -> 230882.61 | F17: =SUM(Repayment!E47:E58) -> 199232.8 | G17: =SUM(Repayment!E59:E70) -> 163745.13 | H17: =SUM(Repayment!E71:E82) -> 123954.28 | I17: =SUM(Repayment!E83:E94) -> 79338.41
B18: Depreciation on Building | C18: =Depreciation!C4 -> 52500 | D18: =Depreciation!C5 -> 47250 | E18: =Depreciation!C6 -> 42525 | F18: =Depreciation!C7 -> 38272.5 | G18: =Depreciation!C8 -> 34445.25 | H18: =Depreciation!C9 -> 31000.725 | I18: =Depreciation!C10 -> 27900.653
B19: Depreciation on Equipments | C19: =Depreciation!F4 -> 7965 | D19: =Depreciation!F5 -> 6770.25 | E19: =Depreciation!F6 -> 5754.7125 | F19: =Depreciation!F7 -> 4891.5056 | G19: =Depreciation!F8 -> 4157.7798 | H19: =Depreciation!F9 -> 3534.1128 | I19: =Depreciation!F10 -> 3003.9959
B21: Total Expendiutre | C21: =SUM(C6:C19) -> 1125283.2 | D21: =SUM(D6:D19) -> 1096322.4 | E21: =SUM(E6:E19) -> 1062354.8 | F21: =SUM(F6:F19) -> 1025589.3 | G21: =SUM(G6:G19) -> 985540.66 | H21: =SUM(H6:H19) -> 941681.62 | I21: =SUM(I6:I19) -> 893435.56
B23: Income
B24: By Sale of Male Kids | C24: ='Production Chart'!$D$17*'Techno Economic Parameters'!$C$95 -> 1424000 | D24: ='Production Chart'!$D$17*'Techno Economic Parameters'!$C$95 -> 1424000 | E24: ='Production Chart'!$D$17*'Techno Economic Parameters'!$C$95 -> 1424000 | F24: ='Production Chart'!$D$17*'Techno Economic Parameters'!$C$95 -> 1424000 | G24: ='Production Chart'!$D$17*'Techno Economic Parameters'!$C$95 -> 1424000 | H24: ='Production Chart'!$D$17*'Techno Economic Parameters'!$C$95 -> 1424000 | I24: ='Production Chart'!$D$17*'Techno Economic Parameters'!$C$95 -> 1424000
B25: By Sale of Female Kids | C25: ='Production Chart'!$D$18*'Techno Economic Parameters'!$C$96 -> 1232000 | D25: ='Production Chart'!$D$18*'Techno Economic Parameters'!$C$96 -> 1232000 | E25: ='Production Chart'!$D$18*'Techno Economic Parameters'!$C$96 -> 1232000 | F25: ='Production Chart'!$D$18*'Techno Economic Parameters'!$C$96 -> 1232000 | G25: ='Production Chart'!$D$18*'Techno Economic Parameters'!$C$96 -> 1232000 | H25: ='Production Chart'!$D$18*'Techno Economic Parameters'!$C$96 -> 1232000 | I25: ='Production Chart'!$D$18*'Techno Economic Parameters'!$C$96 -> 1232000
B26: By Sale of Mannue | C26: ='Techno Economic Parameters'!$C$98*('Techno Economic Parameters'!$C$11+'Techno Economic Parameters'!$D$11) -> 5250 | D26: ='Techno Economic Parameters'!$C$98*('Techno Economic Parameters'!$C$11+'Techno Economic Parameters'!$D$11) -> 5250 | E26: ='Techno Economic Parameters'!$C$98*('Techno Economic Parameters'!$C$11+'Techno Economic Parameters'!$D$11) -> 5250 | F26: ='Techno Economic Parameters'!$C$98*('Techno Economic Parameters'!$C$11+'Techno Economic Parameters'!$D$11) -> 5250 | G26: ='Techno Economic Parameters'!$C$98*('Techno Economic Parameters'!$C$11+'Techno Economic Parameters'!$D$11) -> 5250 | H26: ='Techno Economic Parameters'!$C$98*('Techno Economic Parameters'!$C$11+'Techno Economic Parameters'!$D$11) -> 5250 | I26: ='Techno Economic Parameters'!$C$98*('Techno Economic Parameters'!$C$11+'Techno Economic Parameters'!$D$11) -> 5250
B27: My Sale of Culled Animals | C27: ='Techno Economic Parameters'!$C$97*('Production Chart'!$D$19+'Production Chart'!$D$20) -> 35000 | D27: ='Techno Economic Parameters'!$C$97*('Production Chart'!$D$19+'Production Chart'!$D$20) -> 35000 | E27: ='Techno Economic Parameters'!$C$97*('Production Chart'!$D$19+'Production Chart'!$D$20) -> 35000 | F27: ='Techno Economic Parameters'!$C$97*('Production Chart'!$D$19+'Production Chart'!$D$20) -> 35000 | G27: ='Techno Economic Parameters'!$C$97*('Production Chart'!$D$19+'Production Chart'!$D$20) -> 35000 | H27: ='Techno Economic Parameters'!$C$97*('Production Chart'!$D$19+'Production Chart'!$D$20) -> 35000 | I27: ='Techno Economic Parameters'!$C$97*('Production Chart'!$D$19+'Production Chart'!$D$20) -> 35000
B29: Total Income | C29: =SUM(C24:C28) -> 2696250 | D29: =SUM(D24:D28) -> 2696250 | E29: =SUM(E24:E28) -> 2696250 | F29: =SUM(F24:F28) -> 2696250 | G29: =SUM(G24:G28) -> 2696250 | H29: =SUM(H24:H28) -> 2696250 | I29: =SUM(I24:I28) -> 2696250
B31: Net Income | C31: =C29-C21 -> 1570966.8 | D31: =D29-D21 -> 1599927.6 | E31: =E29-E21 -> 1633895.2 | F31: =F29-F21 -> 1670660.7 | G31: =G29-G21 -> 1710709.3 | H31: =H29-H21 -> 1754568.4 | I31: =I29-I21 -> 1802814.4

Sheet Cash flow
C2: CASH FLOW STATEMENT
C4: I Year | D4: II Year | E4: III Year | F4: IV Year | G4: V Year | H4: VI Year | I4: VII Year
B5: Total Expenditure | C5: ='Expenditure Income '!C21 -> 1125283.2 | D5: ='Expenditure Income '!D21 -> 1096322.4 | E5: ='Expenditure Income '!E21 -> 1062354.8 | F5: ='Expenditure Income '!F21 -> 1025589.3 | G5: ='Expenditure Income '!G21 -> 985540.66 | H5: ='Expenditure Income '!H21 -> 941681.62 | I5: ='Expenditure Income '!I21 -> 893435.56
B6: Total Revenue | C6: ='Expenditure Income '!C29 -> 2696250 | D6: ='Expenditure Income '!D29 -> 2696250 | E6: ='Expenditure Income '!E29 -> 2696250 | F6: ='Expenditure Income '!F29 -> 2696250 | G6: ='Expenditure Income '!G29 -> 2696250 | H6: ='Expenditure Income '!H29 -> 2696250 | I6: ='Expenditure Income '!I29 -> 2696250
B7: Net Revenue | C7: =C6-C5 -> 1570966.8 | D7: =D6-D5 -> 1599927.6 | E7: =E6-E5 -> 1633895.2 | F7: =F6-F5 -> 1670660.7 | G7: =G6-G5 -> 1710709.3 | H7: =H6-H5 -> 1754568.4 | I7: =I6-I5 -> 1802814.4
B10: Interest | C10: ='Expenditure Income '!C17 -> 271125.72 | D10: ='Expenditure Income '!D17 -> 259109.65 | E10: ='Expenditure Income '!E17 -> 230882.61 | F10: ='Expenditure Income '!F17 -> 199232.8 | G10: ='Expenditure Income '!G17 -> 163745.13 | H10: ='Expenditure Income '!H17 -> 123954.28 | I10: ='Expenditure Income '!I17 -> 79338.41
B11: Depreciation | C11: ='Expenditure Income '!C18+'Expenditure Income '!C19 -> 60465 | D11: ='Expenditure Income '!D18+'Expenditure Income '!D19 -> 54020.25 | E11: ='Expenditure Income '!E18+'Expenditure Income '!E19 -> 48279.713 | F11: ='Expenditure Income '!F18+'Expenditure Income '!F19 -> 43164.006 | G11: ='Expenditure Income '!G18+'Expenditure Income '!G19 -> 38603.03 | H11: ='Expenditure Income '!H18+'Expenditure Income '!H19 -> 34534.838 | I11: ='Expenditure Income '!I18+'Expenditure Income '!I19 -> 30904.648
B12: Total (INT + DEP) | C12: =SUM(C10:C11) -> 331590.72 | D12: =SUM(D10:D11) -> 313129.9 | E12: =SUM(E10:E11) -> 279162.32 | F12: =SUM(F10:F11) -> 242396.81 | G12: =SUM(G10:G11) -> 202348.16 | H12: =SUM(H10:H11) -> 158489.12 | I12: =SUM(I10:I11) -> 110243.06
B14: Total Expenditure Without DEP+ INT | C14: =C5-C12 -> 793692.5 | D14: =D5-D12 -> 783192.5 | E14: =E5-E12 -> 783192.5 | F14: =F5-F12 -> 783192.5 | G14: =G5-G12 -> 783192.5 | H14: =H5-H12 -> 783192.5 | I14: =I5-I12 -> 783192.5
B15: Net Revenue After Dep and Int | C15: =C6-(C5-C12) -> 1902557.5 | D15: =D6-(D5-D12) -> 1913057.5 | E15: =E6-(E5-E12) -> 1913057.5 | F15: =F6-(F5-F12) -> 1913057.5 | G15: =G6-(G5-G12) -> 1913057.5 | H15: =H6-(H5-H12) -> 1913057.5 | I15: =I6-(I5-I12) -> 1913057.5

Sheet Repayment
C2: REPAYMENT SCHEDULE
C4: Loan Amount | D4: =Investment!C49 -> 2357615
C5: Rate of Interest per annum | D5: ='Techno Economic Parameters'!C47 -> 11.5 | E5: =D5/12 -> 0.95833333 | F5: per month
C6: Term of loan in Years | D6: ='Techno Economic Parameters'!C48 -> 7 | E6: =D6*12 -> 84 | F6: months
C7: Payment due per year | D7: =(D$5%*$D$4)/(1-1/(1+D$5%)^D6) -> 508431.57 | G7: Year | H7: Principal | I7: Interest | J7: Total | K7: Outstanding Balance
C8: Payment due per month | D8: =ROUND(((D5%/12*D$4))/(1-1/(1+(D$5%/12))^(D$6*12)),0) -> 40991 | G8: First
B9: MONTH | C9: PAYMENT DUE | D9: PRINCIPAL | E9: INTEREST | F9: BALANCE | G9: I | H9: =SUM(D11:D16) -> 0 | I9: =SUM(E11:E16) -> 135562.86 | J9: =SUM(H9:I9) -> 135562.86 | K9: =D4-H9 -> 2357615
F10: =D4 -> 2357615 | G10: II | H10: =SUM(D17:D22) -> 0 | I10: =SUM(E17:E22) -> 135562.86 | J10: =SUM(H10:I10) -> 135562.86 | K10: =K9-H10 -> 2357615
B11: =IF(B10>=D6*12,"",B10+1) -> 1 | C11: =E11 -> 22593.81 | D11: 0 | E11: =IF(B11="","",ROUND(E5%*F10,2)) -> 22593.81 | F11: =IF(B11="","",F10-D11) -> 2357615 | G11: Total | H11: =SUM(H9:H10) -> 0 | I11: =SUM(I9:I10) -> 271125.72 | J11: =SUM(J9:J10) -> 271125.72
B12: =IF(B11>=D6*12,"",B11+1) -> 2 | C12: =E12 -> 22593.81 | D12: 0 | E12: =IF(B12="","",ROUND(E5%*F11,2)) -> 22593.81 | F12: =IF(B12="","",F11-D12) -> 2357615 | G12: Second
B13: =IF(B12>=D6*12,"",B12+1) -> 3 | C13: =E13 -> 22593.81 | D13: 0 | E13: =IF(B13="","",ROUND(E5%*F12,2)) -> 22593.81 | F13: =IF(B13="","",F12-D13) -> 2357615 | G13: I | H13: =SUM(D23:D28) -> 113061.77 | I13: =SUM(E23:E28) -> 132884.23 | J13: =SUM(H13:I13) -> 245946 | K13: =K10-H13 -> 2244553.2
B14: =IF(B13>=D6*12,"",B13+1) -> 4 | C14: =E14 -> 22593.81 | D14: 0 | E14: =IF(B14="","",ROUND(E5%*F13,2)) -> 22593.81 | F14: =IF(B14="","",F13-D14) -> 2357615 | G14: II | H14: =SUM(D29:D34) -> 119720.58 | I14: =SUM(E29:E34) -> 126225.42 | J14: =SUM(H14:I14) -> 245946 | K14: =K13-H14 -> 2124832.6
B15: =IF(B14>=D6*12,"",B14+1) -> 5 | C15: =E15 -> 22593.81 | D15: 0 | E15: =IF(B15="","",ROUND(E5%*F14,2)) -> 22593.81 | F15: =IF(B15="","",F14-D15) -> 2357615 | G15: Total | H15: =SUM(H13:H14) -> 232782.35 | I15: =SUM(I13:I14) -> 259109.65 | J15: =SUM(J13:J14) -> 491892
B16: =IF(B15>=D6*12,"",B15+1) -> 6 | C16: =E16 -> 22593.81 | D16: 0 | E16: =IF(B16="","",ROUND(E5%*F15,2)) -> 22593.81 | F16: =IF(B16="","",F15-D16) -> 2357615 | G16: Third
B17: =IF(B16>=D6*12,"",B16+1) -> 7 | C17: =E17 -> 22593.81 | D17: 0 | E17: =IF(B17="","",ROUND(E5%*F16,2)) -> 22593.81 | F17: =IF(B17="","",F16-D17) -> 2357615 | G17: I | H17: =SUM(D35:D40) -> 126771.57 | I17: =SUM(E35:E40) -> 119174.43 | J17: =SUM(H17:I17) -> 245946 | K17: =K14-H17 -> 1998061.1
B18: =IF(B17>=D6*12,"",B17+1) -> 8 | C18: =E18 -> 22593.81 | D18: 0 | E18: =IF(B18="","",ROUND(E5%*F17,2)) -> 22593.81 | F18: =IF(B18="","",F17-D18) -> 2357615 | G18: II | H18: =SUM(D41:D46) -> 134237.82 | I18: =SUM(E41:E46) -> 111708.18 | J18: =SUM(H18:I18) -> 245946 | K18: =K17-H18 -> 1863823.3
B19: =IF(B18>=D6*12,"",B18+1) -> 9 | C19: =E19 -> 22593.81 | D19: 0 | E19: =IF(B19="","",ROUND(E5%*F18,2)) -> 22593.81 | F19: =IF(B19="","",F18-D19) -> 2357615 | G19: Total | H19: =SUM(H17:H18) -> 261009.39 | I19: =SUM(I17:I18) -> 230882.61 | J19: =SUM(J17:J18) -> 491892
B20: =IF(B19>=D6*12,"",B19+1) -> 10 | C20: =E20 -> 22593.81 | D20: 0 | E20: =IF(B20="","",ROUND(E5%*F19,2)) -> 22593.81 | F20: =IF(B20="","",F19-D20) -> 2357615 | G20: Fourth
B21: =IF(B20>=D6*12,"",B20+1) -> 11 | C21: =E21 -> 22593.81 | D21: 0 | E21: =IF(B21="","",ROUND(E5%*F20,2)) -> 22593.81 | F21: =IF(B21="","",F20-D21) -> 2357615 | G21: I | H21: =SUM(D47:D52) -> 142143.8 | I21: =SUM(E47:E52) -> 103802.2 | J21: =SUM(H21:I21) -> 245946 | K21: =K18-H21 -> 1721679.5
B22: =IF(B21>=D6*12,"",B21+1) -> 12 | C22: =E22 -> 22593.81 | D22: 0 | E22: =IF(B22="","",ROUND(E5%*F21,2)) -> 22593.81 | F22: =IF(B22="","",F21-D22) -> 2357615 | G22: II | H22: =SUM(D53:D58) -> 150515.4 | I22: =SUM(E53:E58) -> 95430.6 | J22: =SUM(H22:I22) -> 245946 | K22: =K21-H22 -> 1571164.1
B23: =IF(B22>=D6*12,"",B22+1) -> 13 | C23: =IF(B23="","",IF(OR(B23=E6,D8>ROUND((1+E5%)*F22,2)),ROUND((1+E5%)*F22,2),D8)) -> 40991 | D23: =IF(B23="","",C23-E23) -> 18397.19 | E23: =IF(B23="","",ROUND(E5%*F22,2)) -> 22593.81 | F23: =IF(B23="","",F22-D23) -> 2339217.8 | G23: Total | H23: =SUM(H21:H22) -> 292659.2 | I23: =SUM(I21:I22) -> 199232.8 | J23: =SUM(J21:J22) -> 491892
B24: =IF(B23>=D6*12,"",B23+1) -> 14 | C24: =IF(B24="","",IF(OR(B24=E6,D8>ROUND((1+E5%)*F23,2)),ROUND((1+E5%)*F23,2),D8)) -> 40991 | D24: =IF(B24="","",C24-E24) -> 18573.5 | E24: =IF(B24="","",ROUND(E5%*F23,2)) -> 22417.5 | F24: =IF(B24="","",F23-D24) -> 2320644.3 | G24: Fifth
B25: =IF(B24>=D6*12,"",B24+1) -> 15 | C25: =IF(B25="","",IF(OR(B25=E6,D8>ROUND((1+E5%)*F24,2)),ROUND((1+E5%)*F24,2),D8)) -> 40991 | D25: =IF(B25="","",C25-E25) -> 18751.49 | E25: =IF(B25="","",ROUND(E5%*F24,2)) -> 22239.51 | F25: =IF(B25="","",F24-D25) -> 2301892.8 | G25: I | H25: =SUM(D59:D64) -> 159380.06 | I25: =SUM(E59:E64) -> 86565.94 | J25: =SUM(H25:I25) -> 245946 | K25: =K22-H25 -> 1411784
B26: =IF(B25>=D6*12,"",B25+1) -> 16 | C26: =IF(B26="","",IF(OR(B26=E6,D8>ROUND((1+E5%)*F25,2)),ROUND((1+E5%)*F25,2),D8)) -> 40991 | D26: =IF(B26="","",C26-E26) -> 18931.19 | E26: =IF(B26="","",ROUND(E5%*F25,2)) -> 22059.81 | F26: =IF(B26="","",F25-D26) -> 2282961.6 | G26: II | H26: =SUM(D65:D70) -> 168766.81 | I26: =SUM(E65:E70) -> 77179.19 | J26: =SUM(H26:I26) -> 245946 | K26: =K25-H26 -> 1243017.2
B27: =IF(B26>=D6*12,"",B26+1) -> 17 | C27: =IF(B27="","",IF(OR(B27=E6,D8>ROUND((1+E5%)*F26,2)),ROUND((1+E5%)*F26,2),D8)) -> 40991 | D27: =IF(B27="","",C27-E27) -> 19112.62 | E27: =IF(B27="","",ROUND(E5%*F26,2)) -> 21878.38 | F27: =IF(B27="","",F26-D27) -> 2263849 | G27: Total | H27: =SUM(H25:H26) -> 328146.87 | I27: =SUM(I25:I26) -> 163745.13 | J27: =SUM(J25:J26) -> 491892
B28: =IF(B27>=D6*12,"",B27+1) -> 18 | C28: =IF(B28="","",IF(OR(B28=E6,D8>ROUND((1+E5%)*F27,2)),ROUND((1+E5%)*F27,2),D8)) -> 40991 | D28: =IF(B28="","",C28-E28) -> 19295.78 | E28: =IF(B28="","",ROUND(E5%*F27,2)) -> 21695.22 | F28: =IF(B28="","",F27-D28) -> 2244553.2 | G28: Sixth
B29: =IF(B28>=D6*12,"",B28+1) -> 19 | C29: =IF(B29="","",IF(OR(B29=E6,D8>ROUND((1+E5%)*F28,2)),ROUND((1+E5%)*F28,2),D8)) -> 40991 | D29: =IF(B29="","",C29-E29) -> 19480.7 | E29: =IF(B29="","",ROUND(E5%*F28,2)) -> 21510.3 | F29: =IF(B29="","",F28-D29) -> 2225072.5 | G29: I | H29: =SUM(D71:D76) -> 178706.37 | I29: =SUM(E71:E76) -> 67239.63 | J29: =SUM(H29:I29) -> 245946 | K29: =K26-H29 -> 1064310.8
B30: =IF(B29>=D6*12,"",B29+1) -> 20 | C30: =IF(B30="","",IF(OR(B30=E6,D8>ROUND((1+E5%)*F29,2)),ROUND((1+E5%)*F29,2),D8)) -> 40991 | D30: =IF(B30="","",C30-E30) -> 19667.39 | E30: =IF(B30="","",ROUND(E5%*F29,2)) -> 21323.61 | F30: =IF(B30="","",F29-D30) -> 2205405.1 | G30: II | H30: =SUM(D77:D82) -> 189231.35 | I30: =SUM(E77:E82) -> 56714.65 | J30: =SUM(H30:I30) -> 245946 | K30: =K29-H30 -> 875079.47
B31: =IF(B30>=D6*12,"",B30+1) -> 21 | C31: =IF(B31="","",IF(OR(B31=E6,D8>ROUND((1+E5%)*F30,2)),ROUND((1+E5%)*F30,2),D8)) -> 40991 | D31: =IF(B31="","",C31-E31) -> 19855.87 | E31: =IF(B31="","",ROUND(E5%*F30,2)) -> 21135.13 | F31: =IF(B31="","",F30-D31) -> 2185549.3 | G31: Total | H31: =SUM(H29:H30) -> 367937.72 | I31: =SUM(I29:I30) -> 123954.28 | J31: =SUM(J29:J30) -> 491892
B32: =IF(B31>=D6*12,"",B31+1) -> 22 | C32: =IF(B32="","",IF(OR(B32=E6,D8>ROUND((1+E5%)*F31,2)),ROUND((1+E5%)*F31,2),D8)) -> 40991 | D32: =IF(B32="","",C32-E32) -> 20046.15 | E32: =IF(B32="","",ROUND(E5%*F31,2)) -> 20944.85 | F32: =IF(B32="","",F31-D32) -> 2165503.1 | G32: Seventh
B33: =IF(B32>=D6*12,"",B32+1) -> 23 | C33: =IF(B33="","",IF(OR(B33=E6,D8>ROUND((1+E5%)*F32,2)),ROUND((1+E5%)*F32,2),D8)) -> 40991 | D33: =IF(B33="","",C33-E33) -> 20238.26 | E33: =IF(B33="","",ROUND(E5%*F32,2)) -> 20752.74 | F33: =IF(B33="","",F32-D33) -> 2145264.9 | G33: I | H33: =SUM(D83:D88) -> 200376.18 | I33: =SUM(E83:E88) -> 45569.82 | J33: =SUM(H33:I33) -> 245946 | K33: =K30-H33 -> 674703.29
B34: =IF(B33>=D6*12,"",B33+1) -> 24 | C34: =IF(B34="","",IF(OR(B34=E6,D8>ROUND((1+E5%)*F33,2)),ROUND((1+E5%)*F33,2),D8)) -> 40991 | D34: =IF(B34="","",C34-E34) -> 20432.21 | E34: =IF(B34="","",ROUND(E5%*F33,2)) -> 20558.79 | F34: =IF(B34="","",F33-D34) -> 2124832.6 | G34: II | H34: =SUM(D89:D94) -> 674703.29 | I34: =SUM(E89:E94) -> 33768.59 | J34: =SUM(H34:I34) -> 708471.88 | K34: =K33-H34 -> 0
B35: =IF(B34>=D6*12,"",B34+1) -> 25 | C35: =IF(B35="","",IF(OR(B35=E6,D8>ROUND((1+E5%)*F34,2)),ROUND((1+E5%)*F34,2),D8)) -> 40991 | D35: =IF(B35="","",C35-E35) -> 20628.02 | E35: =IF(B35="","",ROUND(E5%*F34,2)) -> 20362.98 | F35: =IF(B35="","",F34-D35) -> 2104204.6 | G35: Total | H35: =SUM(H33:H34) -> 875079.47 | I35: =SUM(I33:I34) -> 79338.41 | J35: =SUM(J33:J34) -> 954417.88
B36: =IF(B35>=D6*12,"",B35+1) -> 26 | C36: =IF(B36="","",IF(OR(B36=E6,D8>ROUND((1+E5%)*F35,2)),ROUND((1+E5%)*F35,2),D8)) -> 40991 | D36: =IF(B36="","",C36-E36) -> 20825.71 | E36: =IF(B36="","",ROUND(E5%*F35,2)) -> 20165.29 | F36: =IF(B36="","",F35-D36) -> 2083378.9
B37: =IF(B36>=D6*12,"",B36+1) -> 27 | C37: =IF(B37="","",IF(OR(B37=E6,D8>ROUND((1+E5%)*F36,2)),ROUND((1+E5%)*F36,2),D8)) -> 40991 | D37: =IF(B37="","",C37-E37) -> 21025.29 | E37: =IF(B37="","",ROUND(E5%*F36,2)) -> 19965.71 | F37: =IF(B37="","",F36-D37) -> 2062353.6
B38: =IF(B37>=D6*12,"",B37+1) -> 28 | C38: =IF(B38="","",IF(OR(B38=E6,D8>ROUND((1+E5%)*F37,2)),ROUND((1+E5%)*F37,2),D8)) -> 40991 | D38: =IF(B38="","",C38-E38) -> 21226.78 | E38: =IF(B38="","",ROUND(E5%*F37,2)) -> 19764.22 | F38: =IF(B38="","",F37-D38) -> 2041126.8
B39: =IF(B38>=D6*12,"",B38+1) -> 29 | C39: =IF(B39="","",IF(OR(B39=E6,D8>ROUND((1+E5%)*F38,2)),ROUND((1+E5%)*F38,2),D8)) -> 40991 | D39: =IF(B39="","",C39-E39) -> 21430.2 | E39: =IF(B39="","",ROUND(E5%*F38,2)) -> 19560.8 | F39: =IF(B39="","",F38-D39) -> 2019696.6
B40: =IF(B39>=D6*12,"",B39+1) -> 30 | C40: =IF(B40="","",IF(OR(B40=E6,D8>ROUND((1+E5%)*F39,2)),ROUND((1+E5%)*F39,2),D8)) -> 40991 | D40: =IF(B40="","",C40-E40) -> 21635.57 | E40: =IF(B40="","",ROUND(E5%*F39,2)) -> 19355.43 | F40: =IF(B40="","",F39-D40) -> 1998061.1
B41: =IF(B40>=D6*12,"",B40+1) -> 31 | C41: =IF(B41="","",IF(OR(B41=E6,D8>ROUND((1+E5%)*F40,2)),ROUND((1+E5%)*F40,2),D8)) -> 40991 | D41: =IF(B41="","",C41-E41) -> 21842.91 | E41: =IF(B41="","",ROUND(E5%*F40,2)) -> 19148.09 | F41: =IF(B41="","",F40-D41) -> 1976218.2
B42: =IF(B41>=D6*12,"",B41+1) -> 32 | C42: =IF(B42="","",IF(OR(B42=E6,D8>ROUND((1+E5%)*F41,2)),ROUND((1+E5%)*F41,2),D8)) -> 40991 | D42: =IF(B42="","",C42-E42) -> 22052.24 | E42: =IF(B42="","",ROUND(E5%*F41,2)) -> 18938.76 | F42: =IF(B42="","",F41-D42) -> 1954165.9
B43: =IF(B42>=D6*12,"",B42+1) -> 33 | C43: =IF(B43="","",IF(OR(B43=E6,D8>ROUND((1+E5%)*F42,2)),ROUND((1+E5%)*F42,2),D8)) -> 40991 | D43: =IF(B43="","",C43-E43) -> 22263.58 | E43: =IF(B43="","",ROUND(E5%*F42,2)) -> 18727.42 | F43: =IF(B43="","",F42-D43) -> 1931902.3
B44: =IF(B43>=D6*12,"",B43+1) -> 34 | C44: =IF(B44="","",IF(OR(B44=E6,D8>ROUND((1+E5%)*F43,2)),ROUND((1+E5%)*F43,2),D8)) -> 40991 | D44: =IF(B44="","",C44-E44) -> 22476.94 | E44: =IF(B44="","",ROUND(E5%*F43,2)) -> 18514.06 | F44: =IF(B44="","",F43-D44) -> 1909425.4
B45: =IF(B44>=D6*12,"",B44+1) -> 35 | C45: =IF(B45="","",IF(OR(B45=E6,D8>ROUND((1+E5%)*F44,2)),ROUND((1+E5%)*F44,2),D8)) -> 40991 | D45: =IF(B45="","",C45-E45) -> 22692.34 | E45: =IF(B45="","",ROUND(E5%*F44,2)) -> 18298.66 | F45: =IF(B45="","",F44-D45) -> 1886733.1
B46: =IF(B45>=D6*12,"",B45+1) -> 36 | C46: =IF(B46="","",IF(OR(B46=E6,D8>ROUND((1+E5%)*F45,2)),ROUND((1+E5%)*F45,2),D8)) -> 40991 | D46: =IF(B46="","",C46-E46) -> 22909.81 | E46: =IF(B46="","",ROUND(E5%*F45,2)) -> 18081.19 | F46: =IF(B46="","",F45-D46) -> 1863823.3
B47: =IF(B46>=D6*12,"",B46+1) -> 37 | C47: =IF(B47="","",IF(OR(B47=E6,D8>ROUND((1+E5%)*F46,2)),ROUND((1+E5%)*F46,2),D8)) -> 40991 | D47: =IF(B47="","",C47-E47) -> 23129.36 | E47: =IF(B47="","",ROUND(E5%*F46,2)) -> 17861.64 | F47: =IF(B47="","",F46-D47) -> 1840693.9
B48: =IF(B47>=D6*12,"",B47+1) -> 38 | C48: =IF(B48="","",IF(OR(B48=E6,D8>ROUND((1+E5%)*F47,2)),ROUND((1+E5%)*F47,2),D8)) -> 40991 | D48: =IF(B48="","",C48-E48) -> 23351.02 | E48: =IF(B48="","",ROUND(E5%*F47,2)) -> 17639.98 | F48: =IF(B48="","",F47-D48) -> 1817342.9
B49: =IF(B48>=D6*12,"",B48+1) -> 39 | C49: =IF(B49="","",IF(OR(B49=E6,D8>ROUND((1+E5%)*F48,2)),ROUND((1+E5%)*F48,2),D8)) -> 40991 | D49: =IF(B49="","",C49-E49) -> 23574.8 | E49: =IF(B49="","",ROUND(E5%*F48,2)) -> 17416.2 | F49: =IF(B49="","",F48-D49) -> 1793768.1
B50: =IF(B49>=D6*12,"",B49+1) -> 40 | C50: =IF(B50="","",IF(OR(B50=E6,D8>ROUND((1+E5%)*F49,2)),ROUND((1+E5%)*F49,2),D8)) -> 40991 | D50: =IF(B50="","",C50-E50) -> 23800.72 | E50: =IF(B50="","",ROUND(E5%*F49,2)) -> 17190.28 | F50: =IF(B50="","",F49-D50) -> 1769967.4
B51: =IF(B50>=D6*12,"",B50+1) -> 41 | C51: =IF(B51="","",IF(OR(B51=E6,D8>ROUND((1+E5%)*F50,2)),ROUND((1+E5%)*F50,2),D8)) -> 40991 | D51: =IF(B51="","",C51-E51) -> 24028.81 | E51: =IF(B51="","",ROUND(E5%*F50,2)) -> 16962.19 | F51: =IF(B51="","",F50-D51) -> 1745938.5
B52: =IF(B51>=D6*12,"",B51+1) -> 42 | C52: =IF(B52="","",IF(OR(B52=E6,D8>ROUND((1+E5%)*F51,2)),ROUND((1+E5%)*F51,2),D8)) -> 40991 | D52: =IF(B52="","",C52-E52) -> 24259.09 | E52: =IF(B52="","",ROUND(E5%*F51,2)) -> 16731.91 | F52: =IF(B52="","",F51-D52) -> 1721679.5
B53: =IF(B52>=D6*12,"",B52+1) -> 43 | C53: =IF(B53="","",IF(OR(B53=E6,D8>ROUND((1+E5%)*F52,2)),ROUND((1+E5%)*F52,2),D8)) -> 40991 | D53: =IF(B53="","",C53-E53) -> 24491.57 | E53: =IF(B53="","",ROUND(E5%*F52,2)) -> 16499.43 | F53: =IF(B53="","",F52-D53) -> 1697187.9
B54: =IF(B53>=D6*12,"",B53+1) -> 44 | C54: =IF(B54="","",IF(OR(B54=E6,D8>ROUND((1+E5%)*F53,2)),ROUND((1+E5%)*F53,2),D8)) -> 40991 | D54: =IF(B54="","",C54-E54) -> 24726.28 | E54: =IF(B54="","",ROUND(E5%*F53,2)) -> 16264.72 | F54: =IF(B54="","",F53-D54) -> 1672461.6
B55: =IF(B54>=D6*12,"",B54+1) -> 45 | C55: =IF(B55="","",IF(OR(B55=E6,D8>ROUND((1+E5%)*F54,2)),ROUND((1+E5%)*F54,2),D8)) -> 40991 | D55: =IF(B55="","",C55-E55) -> 24963.24 | E55: =IF(B55="","",ROUND(E5%*F54,2)) -> 16027.76 | F55: =IF(B55="","",F54-D55) -> 1647498.4
B56: =IF(B55>=D6*12,"",B55+1) -> 46 | C56: =IF(B56="","",IF(OR(B56=E6,D8>ROUND((1+E5%)*F55,2)),ROUND((1+E5%)*F55,2),D8)) -> 40991 | D56: =IF(B56="","",C56-E56) -> 25202.47 | E56: =IF(B56="","",ROUND(E5%*F55,2)) -> 15788.53 | F56: =IF(B56="","",F55-D56) -> 1622295.9
B57: =IF(B56>=D6*12,"",B56+1) -> 47 | C57: =IF(B57="","",IF(OR(B57=E6,D8>ROUND((1+E5%)*F56,2)),ROUND((1+E5%)*F56,2),D8)) -> 40991 | D57: =IF(B57="","",C57-E57) -> 25444 | E57: =IF(B57="","",ROUND(E5%*F56,2)) -> 15547 | F57: =IF(B57="","",F56-D57) -> 1596851.9
B58: =IF(B57>=D6*12,"",B57+1) -> 48 | C58: =IF(B58="","",IF(OR(B58=E6,D8>ROUND((1+E5%)*F57,2)),ROUND((1+E5%)*F57,2),D8)) -> 40991 | D58: =IF(B58="","",C58-E58) -> 25687.84 | E58: =IF(B58="","",ROUND(E5%*F57,2)) -> 15303.16 | F58: =IF(B58="","",F57-D58) -> 1571164.1
B59: =IF(B58>=D6*12,"",B58+1) -> 49 | C59: =IF(B59="","",IF(OR(B59=E6,D8>ROUND((1+E5%)*F58,2)),ROUND((1+E5%)*F58,2),D8)) -> 40991 | D59: =IF(B59="","",C59-E59) -> 25934.01 | E59: =IF(B59="","",ROUND(E5%*F58,2)) -> 15056.99 | F59: =IF(B59="","",F58-D59) -> 1545230
B60: =IF(B59>=D6*12,"",B59+1) -> 50 | C60: =IF(B60="","",IF(OR(B60=E6,D8>ROUND((1+E5%)*F59,2)),ROUND((1+E5%)*F59,2),D8)) -> 40991 | D60: =IF(B60="","",C60-E60) -> 26182.55 | E60: =IF(B60="","",ROUND(E5%*F59,2)) -> 14808.45 | F60: =IF(B60="","",F59-D60) -> 1519047.5
B61: =IF(B60>=D6*12,"",B60+1) -> 51 | C61: =IF(B61="","",IF(OR(B61=E6,D8>ROUND((1+E5%)*F60,2)),ROUND((1+E5%)*F60,2),D8)) -> 40991 | D61: =IF(B61="","",C61-E61) -> 26433.46 | E61: =IF(B61="","",ROUND(E5%*F60,2)) -> 14557.54 | F61: =IF(B61="","",F60-D61) -> 1492614
B62: =IF(B61>=D6*12,"",B61+1) -> 52 | C62: =IF(B62="","",IF(OR(B62=E6,D8>ROUND((1+E5%)*F61,2)),ROUND((1+E5%)*F61,2),D8)) -> 40991 | D62: =IF(B62="","",C62-E62) -> 26686.78 | E62: =IF(B62="","",ROUND(E5%*F61,2)) -> 14304.22 | F62: =IF(B62="","",F61-D62) -> 1465927.3
B63: =IF(B62>=D6*12,"",B62+1) -> 53 | C63: =IF(B63="","",IF(OR(B63=E6,D8>ROUND((1+E5%)*F62,2)),ROUND((1+E5%)*F62,2),D8)) -> 40991 | D63: =IF(B63="","",C63-E63) -> 26942.53 | E63: =IF(B63="","",ROUND(E5%*F62,2)) -> 14048.47 | F63: =IF(B63="","",F62-D63) -> 1438984.7
B64: =IF(B63>=D6*12,"",B63+1) -> 54 | C64: =IF(B64="","",IF(OR(B64=E6,D8>ROUND((1+E5%)*F63,2)),ROUND((1+E5%)*F63,2),D8)) -> 40991 | D64: =IF(B64="","",C64-E64) -> 27200.73 | E64: =IF(B64="","",ROUND(E5%*F63,2)) -> 13790.27 | F64: =IF(B64="","",F63-D64) -> 1411784
B65: =IF(B64>=D6*12,"",B64+1) -> 55 | C65: =IF(B65="","",IF(OR(B65=E6,D8>ROUND((1+E5%)*F64,2)),ROUND((1+E5%)*F64,2),D8)) -> 40991 | D65: =IF(B65="","",C65-E65) -> 27461.4 | E65: =IF(B65="","",ROUND(E5%*F64,2)) -> 13529.6 | F65: =IF(B65="","",F64-D65) -> 1384322.6
B66: =IF(B65>=D6*12,"",B65+1) -> 56 | C66: =IF(B66="","",IF(OR(B66=E6,D8>ROUND((1+E5%)*F65,2)),ROUND((1+E5%)*F65,2),D8)) -> 40991 | D66: =IF(B66="","",C66-E66) -> 27724.58 | E66: =IF(B66="","",ROUND(E5%*F65,2)) -> 13266.42 | F66: =IF(B66="","",F65-D66) -> 1356598
B67: =IF(B66>=D6*12,"",B66+1) -> 57 | C67: =IF(B67="","",IF(OR(B67=E6,D8>ROUND((1+E5%)*F66,2)),ROUND((1+E5%)*F66,2),D8)) -> 40991 | D67: =IF(B67="","",C67-E67) -> 27990.27 | E67: =IF(B67="","",ROUND(E5%*F66,2)) -> 13000.73 | F67: =IF(B67="","",F66-D67) -> 1328607.7
B68: =IF(B67>=D6*12,"",B67+1) -> 58 | C68: =IF(B68="","",IF(OR(B68=E6,D8>ROUND((1+E5%)*F67,2)),ROUND((1+E5%)*F67,2),D8)) -> 40991 | D68: =IF(B68="","",C68-E68) -> 28258.51 | E68: =IF(B68="","",ROUND(E5%*F67,2)) -> 12732.49 | F68: =IF(B68="","",F67-D68) -> 1300349.2
B69: =IF(B68>=D6*12,"",B68+1) -> 59 | C69: =IF(B69="","",IF(OR(B69=E6,D8>ROUND((1+E5%)*F68,2)),ROUND((1+E5%)*F68,2),D8)) -> 40991 | D69: =IF(B69="","",C69-E69) -> 28529.32 | E69: =IF(B69="","",ROUND(E5%*F68,2)) -> 12461.68 | F69: =IF(B69="","",F68-D69) -> 1271819.9
B70: =IF(B69>=D6*12,"",B69+1) -> 60 | C70: =IF(B70="","",IF(OR(B70=E6,D8>ROUND((1+E5%)*F69,2)),ROUND((1+E5%)*F69,2),D8)) -> 40991 | D70: =IF(B70="","",C70-E70) -> 28802.73 | E70: =IF(B70="","",ROUND(E5%*F69,2)) -> 12188.27 | F70: =IF(B70="","",F69-D70) -> 1243017.2
B71: =IF(B70>=D6*12,"",B70+1) -> 61 | C71: =IF(B71="","",IF(OR(B71=E6,D8>ROUND((1+E5%)*F70,2)),ROUND((1+E5%)*F70,2),D8)) -> 40991 | D71: =IF(B71="","",C71-E71) -> 29078.75 | E71: =IF(B71="","",ROUND(E5%*F70,2)) -> 11912.25 | F71: =IF(B71="","",F70-D71) -> 1213938.4
B72: =IF(B71>=D6*12,"",B71+1) -> 62 | C72: =IF(B72="","",IF(OR(B72=E6,D8>ROUND((1+E5%)*F71,2)),ROUND((1+E5%)*F71,2),D8)) -> 40991 | D72: =IF(B72="","",C72-E72) -> 29357.42 | E72: =IF(B72="","",ROUND(E5%*F71,2)) -> 11633.58 | F72: =IF(B72="","",F71-D72) -> 1184581
B73: =IF(B72>=D6*12,"",B72+1) -> 63 | C73: =IF(B73="","",IF(OR(B73=E6,D8>ROUND((1+E5%)*F72,2)),ROUND((1+E5%)*F72,2),D8)) -> 40991 | D73: =IF(B73="","",C73-E73) -> 29638.77 | E73: =IF(B73="","",ROUND(E5%*F72,2)) -> 11352.23 | F73: =IF(B73="","",F72-D73) -> 1154942.2
B74: =IF(B73>=D6*12,"",B73+1) -> 64 | C74: =IF(B74="","",IF(OR(B74=E6,D8>ROUND((1+E5%)*F73,2)),ROUND((1+E5%)*F73,2),D8)) -> 40991 | D74: =IF(B74="","",C74-E74) -> 29922.8 | E74: =IF(B74="","",ROUND(E5%*F73,2)) -> 11068.2 | F74: =IF(B74="","",F73-D74) -> 1125019.4
B75: =IF(B74>=D6*12,"",B74+1) -> 65 | C75: =IF(B75="","",IF(OR(B75=E6,D8>ROUND((1+E5%)*F74,2)),ROUND((1+E5%)*F74,2),D8)) -> 40991 | D75: =IF(B75="","",C75-E75) -> 30209.56 | E75: =IF(B75="","",ROUND(E5%*F74,2)) -> 10781.44 | F75: =IF(B75="","",F74-D75) -> 1094809.9
B76: =IF(B75>=D6*12,"",B75+1) -> 66 | C76: =IF(B76="","",IF(OR(B76=E6,D8>ROUND((1+E5%)*F75,2)),ROUND((1+E5%)*F75,2),D8)) -> 40991 | D76: =IF(B76="","",C76-E76) -> 30499.07 | E76: =IF(B76="","",ROUND(E5%*F75,2)) -> 10491.93 | F76: =IF(B76="","",F75-D76) -> 1064310.8
B77: =IF(B76>=D6*12,"",B76+1) -> 67 | C77: =IF(B77="","",IF(OR(B77=E6,D8>ROUND((1+E5%)*F76,2)),ROUND((1+E5%)*F76,2),D8)) -> 40991 | D77: =IF(B77="","",C77-E77) -> 30791.35 | E77: =IF(B77="","",ROUND(E5%*F76,2)) -> 10199.65 | F77: =IF(B77="","",F76-D77) -> 1033519.5
B78: =IF(B77>=D6*12,"",B77+1) -> 68 | C78: =IF(B78="","",IF(OR(B78=E6,D8>ROUND((1+E5%)*F77,2)),ROUND((1+E5%)*F77,2),D8)) -> 40991 | D78: =IF(B78="","",C78-E78) -> 31086.44 | E78: =IF(B78="","",ROUND(E5%*F77,2)) -> 9904.56 | F78: =IF(B78="","",F77-D78) -> 1002433
B79: =IF(B78>=D6*12,"",B78+1) -> 69 | C79: =IF(B79="","",IF(OR(B79=E6,D8>ROUND((1+E5%)*F78,2)),ROUND((1+E5%)*F78,2),D8)) -> 40991 | D79: =IF(B79="","",C79-E79) -> 31384.35 | E79: =IF(B79="","",ROUND(E5%*F78,2)) -> 9606.65 | F79: =IF(B79="","",F78-D79) -> 971048.68
B80: =IF(B79>=D6*12,"",B79+1) -> 70 | C80: =IF(B80="","",IF(OR(B80=E6,D8>ROUND((1+E5%)*F79,2)),ROUND((1+E5%)*F79,2),D8)) -> 40991 | D80: =IF(B80="","",C80-E80) -> 31685.12 | E80: =IF(B80="","",ROUND(E5%*F79,2)) -> 9305.88 | F80: =IF(B80="","",F79-D80) -> 939363.56
B81: =IF(B80>=D6*12,"",B80+1) -> 71 | C81: =IF(B81="","",IF(OR(B81=E6,D8>ROUND((1+E5%)*F80,2)),ROUND((1+E5%)*F80,2),D8)) -> 40991 | D81: =IF(B81="","",C81-E81) -> 31988.77 | E81: =IF(B81="","",ROUND(E5%*F80,2)) -> 9002.23 | F81: =IF(B81="","",F80-D81) -> 907374.79
B82: =IF(B81>=D6*12,"",B81+1) -> 72 | C82: =IF(B82="","",IF(OR(B82=E6,D8>ROUND((1+E5%)*F81,2)),ROUND((1+E5%)*F81,2),D8)) -> 40991 | D82: =IF(B82="","",C82-E82) -> 32295.32 | E82: =IF(B82="","",ROUND(E5%*F81,2)) -> 8695.68 | F82: =IF(B82="","",F81-D82) -> 875079.47
B83: =IF(B82>=D6*12,"",B82+1) -> 73 | C83: =IF(B83="","",IF(OR(B83=E6,D8>ROUND((1+E5%)*F82,2)),ROUND((1+E5%)*F82,2),D8)) -> 40991 | D83: =IF(B83="","",C83-E83) -> 32604.82 | E83: =IF(B83="","",ROUND(E5%*F82,2)) -> 8386.18 | F83: =IF(B83="","",F82-D83) -> 842474.65
B84: =IF(B83>=D6*12,"",B83+1) -> 74 | C84: =IF(B84="","",IF(OR(B84=E6,D8>ROUND((1+E5%)*F83,2)),ROUND((1+E5%)*F83,2),D8)) -> 40991 | D84: =IF(B84="","",C84-E84) -> 32917.28 | E84: =IF(B84="","",ROUND(E5%*F83,2)) -> 8073.72 | F84: =IF(B84="","",F83-D84) -> 809557.37
B85: =IF(B84>=D6*12,"",B84+1) -> 75 | C85: =IF(B85="","",IF(OR(B85=E6,D8>ROUND((1+E5%)*F84,2)),ROUND((1+E5%)*F84,2),D8)) -> 40991 | D85: =IF(B85="","",C85-E85) -> 33232.74 | E85: =IF(B85="","",ROUND(E5%*F84,2)) -> 7758.26 | F85: =IF(B85="","",F84-D85) -> 776324.63
B86: =IF(B85>=D6*12,"",B85+1) -> 76 | C86: =IF(B86="","",IF(OR(B86=E6,D8>ROUND((1+E5%)*F85,2)),ROUND((1+E5%)*F85,2),D8)) -> 40991 | D86: =IF(B86="","",C86-E86) -> 33551.22 | E86: =IF(B86="","",ROUND(E5%*F85,2)) -> 7439.78 | F86: =IF(B86="","",F85-D86) -> 742773.41
B87: =IF(B86>=D6*12,"",B86+1) -> 77 | C87: =IF(B87="","",IF(OR(B87=E6,D8>ROUND((1+E5%)*F86,2)),ROUND((1+E5%)*F86,2),D8)) -> 40991 | D87: =IF(B87="","",C87-E87) -> 33872.75 | E87: =IF(B87="","",ROUND(E5%*F86,2)) -> 7118.25 | F87: =IF(B87="","",F86-D87) -> 708900.66
B88: =IF(B87>=D6*12,"",B87+1) -> 78 | C88: =IF(B88="","",IF(OR(B88=E6,D8>ROUND((1+E5%)*F87,2)),ROUND((1+E5%)*F87,2),D8)) -> 40991 | D88: =IF(B88="","",C88-E88) -> 34197.37 | E88: =IF(B88="","",ROUND(E5%*F87,2)) -> 6793.63 | F88: =IF(B88="","",F87-D88) -> 674703.29
B89: =IF(B88>=D6*12,"",B88+1) -> 79 | C89: =IF(B89="","",IF(OR(B89=E6,D8>ROUND((1+E5%)*F88,2)),ROUND((1+E5%)*F88,2),D8)) -> 40991 | D89: =IF(B89="","",C89-E89) -> 34525.09 | E89: =IF(B89="","",ROUND(E5%*F88,2)) -> 6465.91 | F89: =IF(B89="","",F88-D89) -> 640178.2
B90: =IF(B89>=D6*12,"",B89+1) -> 80 | C90: =IF(B90="","",IF(OR(B90=E6,D8>ROUND((1+E5%)*F89,2)),ROUND((1+E5%)*F89,2),D8)) -> 40991 | D90: =IF(B90="","",C90-E90) -> 34855.96 | E90: =IF(B90="","",ROUND(E5%*F89,2)) -> 6135.04 | F90: =IF(B90="","",F89-D90) -> 605322.24
B91: =IF(B90>=D6*12,"",B90+1) -> 81 | C91: =IF(B91="","",IF(OR(B91=E6,D8>ROUND((1+E5%)*F90,2)),ROUND((1+E5%)*F90,2),D8)) -> 40991 | D91: =IF(B91="","",C91-E91) -> 35190 | E91: =IF(B91="","",ROUND(E5%*F90,2)) -> 5801 | F91: =IF(B91="","",F90-D91) -> 570132.24
B92: =IF(B91>=D6*12,"",B91+1) -> 82 | C92: =IF(B92="","",IF(OR(B92=E6,D8>ROUND((1+E5%)*F91,2)),ROUND((1+E5%)*F91,2),D8)) -> 40991 | D92: =IF(B92="","",C92-E92) -> 35527.23 | E92: =IF(B92="","",ROUND(E5%*F91,2)) -> 5463.77 | F92: =IF(B92="","",F91-D92) -> 534605.01
B93: =IF(B92>=D6*12,"",B92+1) -> 83 | C93: =IF(B93="","",IF(OR(B93=E6,D8>ROUND((1+E5%)*F92,2)),ROUND((1+E5%)*F92,2),D8)) -> 40991 | D93: =IF(B93="","",C93-E93) -> 35867.7 | E93: =IF(B93="","",ROUND(E5%*F92,2)) -> 5123.3 | F93: =IF(B93="","",F92-D93) -> 498737.31
B94: =IF(B93>=D6*12,"",B93+1) -> 84 | C94: =IF(B94="","",IF(OR(B94=E6,D8>ROUND((1+E5%)*F93,2)),ROUND((1+E5%)*F93,2),D8)) -> 503516.88 | D94: =IF(B94="","",C94-E94) -> 498737.31 | E94: =IF(B94="","",ROUND(E5%*F93,2)) -> 4779.57 | F94: =IF(B94="","",F93-D94) -> -6.9849193e-10

Sheet Depreciation
D1: DEPRECIATION
C2: Building | E2: Equipment | H2: Depreciation: Decline in value by usage or wear and tear. Buildings 10 % , Equipments 15%
A3: Year | B3: Beginning Value | C3: Rate of Dep. | D3: End Value | E3: Beginning Value | F3: Rate of Dep. | G3: End Value
A4: 1 | B4: =Investment!C8+Investment!C9+Investment!C10+Investment!C11 -> 525000 | C4: =B4*'Techno Economic Parameters'!C70% -> 52500 | D4: =B4-C4 -> 472500 | E4: =Investment!C12+Investment!C13+Investment!C14+Investment!C15+Investment!C16+Investment!C17+Investment!C18+Investment!C19 -> 53100 | F4: =E4*'Techno Economic Parameters'!C71% -> 7965 | G4: =E4-F4 -> 45135
A5: 2 | B5: =D4 -> 472500 | C5: =B5*'Techno Economic Parameters'!C70% -> 47250 | D5: =B5-C5 -> 425250 | E5: =G4 -> 45135 | F5: =E5*'Techno Economic Parameters'!C71% -> 6770.25 | G5: =E5-F5 -> 38364.75
A6: 3 | B6: =D5 -> 425250 | C6: =B6*'Techno Economic Parameters'!C70% -> 42525 | D6: =B6-C6 -> 382725 | E6: =G5 -> 38364.75 | F6: =E6*'Techno Economic Parameters'!C71% -> 5754.7125 | G6: =E6-F6 -> 32610.037
A7: 4 | B7: =D6 -> 382725 | C7: =B7*'Techno Economic Parameters'!C70% -> 38272.5 | D7: =B7-C7 -> 344452.5 | E7: =G6 -> 32610.037 | F7: =E7*'Techno Economic Parameters'!C71% -> 4891.5056 | G7: =E7-F7 -> 27718.532
A8: 5 | B8: =D7 -> 344452.5 | C8: =B8*'Techno Economic Parameters'!C70% -> 34445.25 | D8: =B8-C8 -> 310007.25 | E8: =G7 -> 27718.532 | F8: =E8*'Techno Economic Parameters'!C71% -> 4157.7798 | G8: =E8-F8 -> 23560.752
A9: 6 | B9: =D8 -> 310007.25 | C9: =B9*'Techno Economic Parameters'!C70% -> 31000.725 | D9: =B9-C9 -> 279006.53 | E9: =G8 -> 23560.752 | F9: =E9*'Techno Economic Parameters'!C71% -> 3534.1128 | G9: =E9-F9 -> 20026.639
A10: 7 | B10: =D9 -> 279006.53 | C10: =B10*'Techno Economic Parameters'!C70% -> 27900.653 | D10: =B10-C10 -> 251105.87 | E10: =G9 -> 20026.639 | F10: =E10*'Techno Economic Parameters'!C71% -> 3003.9959 | G10: =E10-F10 -> 17022.643

Sheet Financial Analysis
D2: FINANCIAL ANALYSIS OF THE PROJECT
B3: Net Present Worth and Benefit Cost Ratio
B5: Year | C5: Expenditure | D5: Revenue | E5: Discount Factor | F5: PWof Expenditure | G5: PW of Benefit
B6: 1 | C6: ='Cash flow'!C5 -> 1125283.2 | D6: ='Cash flow'!C6 -> 2696250 | E6: =1/((1+'Techno Economic Parameters'!$C$47%)^'Financial Analysis'!B6) -> 0.89686099 | F6: =C6*E6 -> 1009222.6 | G6: =E6*D6 -> 2418161.4
B7: 2 | C7: ='Cash flow'!D5 -> 1096322.4 | D7: ='Cash flow'!D6 -> 2696250 | E7: =1/((1+'Techno Economic Parameters'!$C$47%)^'Financial Analysis'!B7) -> 0.80435963 | F7: =C7*E7 -> 881837.48 | G7: =E7*D7 -> 2168754.7
B8: 3 | C8: ='Cash flow'!E5 -> 1062354.8 | D8: ='Cash flow'!E6 -> 2696250 | E8: =1/((1+'Techno Economic Parameters'!$C$47%)^'Financial Analysis'!B8) -> 0.72139877 | F8: =C8*E8 -> 766381.46 | G8: =E8*D8 -> 1945071.4
B9: 4 | C9: ='Cash flow'!F5 -> 1025589.3 | D9: ='Cash flow'!F6 -> 2696250 | E9: =1/((1+'Techno Economic Parameters'!$C$47%)^'Financial Analysis'!B9) -> 0.64699441 | F9: =C9*E9 -> 663550.55 | G9: =E9*D9 -> 1744458.7
B10: 5 | C10: ='Cash flow'!G5 -> 985540.66 | D10: ='Cash flow'!G6 -> 2696250 | E10: =1/((1+'Techno Economic Parameters'!$C$47%)^'Financial Analysis'!B10) -> 0.58026405 | F10: =C10*E10 -> 571873.81 | G10: =E10*D10 -> 1564536.9
B11: 6 | C11: ='Cash flow'!H5 -> 941681.62 | D11: ='Cash flow'!H6 -> 2696250 | E11: =1/((1+'Techno Economic Parameters'!$C$47%)^'Financial Analysis'!B11) -> 0.52041619 | F11: =C11*E11 -> 490066.36 | G11: =E11*D11 -> 1403172.1
B12: 7 | C12: ='Cash flow'!I5 -> 893435.56 | D12: ='Cash flow'!I6 -> 2696250 | E12: =1/((1+'Techno Economic Parameters'!$C$47%)^'Financial Analysis'!B12) -> 0.46674097 | F12: =C12*E12 -> 417002.98 | G12: =E12*D12 -> 1258450.4
E14: Total | F14: =SUM(F6:F13) -> 4799935.3 | G14: =SUM(G6:G13) -> 12502606
E15: NPW | F15: =G14-F14 -> 7702670.4
E16: BCR | F16: =G14/F14 -> 2.6047446
B17: Internal Rate of Return
B18: Year | C18: INB | D18: PV of Lower IR | E18: DF Higher IR | F18: PV of Higher IR
B19: 1 | C19: =D6-C6 -> 1570966.8 | D19: =C19*E6 -> 1408938.8 | E19: =1/(((1+(('Techno Economic Parameters'!$C$47+20)%))^'Financial Analysis'!B6)) -> 0.76045627 | F19: =C19*E19 -> 1194651.5
B20: 2 | C20: =D7-C7 -> 1599927.6 | D20: =C20*E7 -> 1286917.2 | E20: =1/(((1+(('Techno Economic Parameters'!$C$47+20)%))^'Financial Analysis'!B7)) -> 0.57829374 | F20: =C20*E20 -> 925228.12
B21: 3 | C21: =D8-C8 -> 1633895.2 | D21: =C21*E8 -> 1178690 | E21: =1/(((1+(('Techno Economic Parameters'!$C$47+20)%))^'Financial Analysis'!B8)) -> 0.43976711 | F21: =C21*E21 -> 718533.35
B22: 4 | C22: =D9-C9 -> 1670660.7 | D22: =C22*E9 -> 1080908.1 | E22: =1/(((1+(('Techno Economic Parameters'!$C$47+20)%))^'Financial Analysis'!B9)) -> 0.33442365 | F22: =C22*E22 -> 558708.46
B23: 5 | C23: =D10-C10 -> 1710709.3 | D23: =C23*E10 -> 992663.13 | E23: =1/(((1+(('Techno Economic Parameters'!$C$47+20)%))^'Financial Analysis'!B10)) -> 0.25431457 | F23: =C23*E23 -> 435058.3
B24: 6 | C24: =D11-C11 -> 1754568.4 | D24: =C24*E11 -> 913105.79 | E24: =1/(((1+(('Techno Economic Parameters'!$C$47+20)%))^'Financial Analysis'!B11)) -> 0.19339511 | F24: =C24*E24 -> 339324.94
B25: 7 | C25: =D12-C12 -> 1802814.4 | D25: =C25*E12 -> 841447.37 | E25: =1/(((1+(('Techno Economic Parameters'!$C$47+20)%))^'Financial Analysis'!B12)) -> 0.14706852 | F25: =C25*E25 -> 265137.26
C27: Total | D27: =SUM(D19:D26) -> 7702670.4 | F27: =SUM(F19:F26) -> 4436642
D28: IRR | E28: =('Techno Economic Parameters'!C47+(((('Techno Economic Parameters'!C47+20)-'Techno Economic Parameters'!C47)*(('Financial Analysis'!D27/('Financial Analysis'!D27+'Financial Analysis'!F27)))))) -> 24.190456 | F28: %
B29: Debt Service Coverage Ratio
B30: Year | C30: Net Income | D30: Total Debt | E30: DSCR Vaue
B31: 1 | C31: ='Cash flow'!C15 -> 1902557.5 | D31: =SUM(Repayment!D11:D22)+'Expenditure Income '!$C$17 -> 271125.72 | E31: =C31/D31 -> 7.017252 | F31: VIABLE OF THE PROJECT
B32: 2 | C32: ='Cash flow'!D15 -> 1913057.5 | D32: =SUM(Repayment!D23:D34)+'Expenditure Income '!$D$17 -> 491892 | E32: =C32/D32 -> 3.889182 | F32: NPW | G32: Positive
B33: 3 | C33: ='Cash flow'!E15 -> 1913057.5 | D33: =SUM(Repayment!D35:D46)+'Expenditure Income '!$E$17 -> 491892 | E33: =C33/D33 -> 3.889182 | F33: BCR | G33: More than one
B34: 4 | C34: ='Cash flow'!F15 -> 1913057.5 | D34: =SUM(Repayment!D47:D58)+'Expenditure Income '!$F$17 -> 491892 | E34: =C34/D34 -> 3.889182 | F34: IRR | G34: More than the lower interest rate
B35: 5 | C35: ='Cash flow'!G15 -> 1913057.5 | D35: =SUM(Repayment!D59:D70)+'Expenditure Income '!$G$17 -> 491892 | E35: =C35/D35 -> 3.889182 | F35: DSCR | G35: Above two
B36: 6 | C36: ='Cash flow'!H15 -> 1913057.5 | D36: =SUM(Repayment!D71:D82)+'Expenditure Income '!$H$17 -> 491892 | E36: =C36/D36 -> 3.889182
B37: 7 | C37: ='Cash flow'!I15 -> 1913057.5 | D37: =SUM(Repayment!D83:D94)+'Expenditure Income '!$I$17 -> 954417.88 | E37: =C37/D37 -> 2.0044234
D38: Average DSCR | E38: =SUM(E31:E37)/'Techno Economic Parameters'!C48 -> 4.0667979
